setup.py
swift_rpc/__init__.py
swift_rpc/aeslib.py
swift_rpc/log.py
swift_rpc/mq.py
swift_rpc/rsalib.py
swift_rpc/serialize.py
swift_rpc.egg-info/PKG-INFO
swift_rpc.egg-info/SOURCES.txt
swift_rpc.egg-info/dependency_links.txt
swift_rpc.egg-info/requires.txt
swift_rpc.egg-info/top_level.txt
swift_rpc/client/__init__.py
swift_rpc/server/__init__.py
swift_rpc/server/handlers.py