Metadata-Version: 1.1
Name: swift-rpc
Version: 2.5
Summary: tornado rpc
Home-page: https://github.com/rfyiamcool
Author: ruifengyun
Author-email: rfyiamcool@163.com
License: MIT
Keywords: tornado,fengyun
Platform: UNKNOWN
Classifier: Development Status :: 2 - Pre-Alpha
Classifier: Intended Audience :: Developers
Classifier: License :: OSI Approved :: MIT License
Classifier: Programming Language :: Python :: 2.7
Classifier: Programming Language :: Python :: 3.0
Classifier: Topic :: Software Development :: Libraries :: Python Modules
